kilroy_module_client_py_sdk/__init__.py
kilroy_module_client_py_sdk/client.py
kilroy_module_client_py_sdk/metrics.py
kilroy_module_client_py_sdk/resources/__init__.py
kilroy_module_client_py_sdk-0.9.0.dist-info/LICENSE
kilroy_module_client_py_sdk-0.9.0.dist-info/WHEEL
kilroy_module_client_py_sdk-0.9.0.dist-info/METADATA
kilroy_module_client_py_sdk-0.9.0.dist-info/RECORD
