Metadata-Version: 2.1
Name: kilroy-module-client-py-sdk
Version: 0.9.0
Summary: SDK for kilroy module clients in Python 🧰
Home-page: https://github.com/kilroybot/kilroy-module-client-py-sdk
Author: kilroy
Author-email: kilroymail@pm.me
Requires-Python: >=3.10,<4.0
Classifier: License :: OSI Approved :: MIT License
Classifier: Operating System :: OS Independent
Classifier: Programming Language :: Python :: 3
Classifier: Programming Language :: Python :: 3.10
Requires-Dist: aiostream (>=0.4,<0.5)
Requires-Dist: kilroy-module-py-shared (>=0.7,<0.8)
Project-URL: Documentation, https://kilroybot.github.io/kilroy-module-client-py-sdk
Project-URL: Repository, https://github.com/kilroybot/kilroy-module-client-py-sdk
